setup.py
genesisclient/__init__.py
genesisclient.egg-info/PKG-INFO
genesisclient.egg-info/SOURCES.txt
genesisclient.egg-info/dependency_links.txt
genesisclient.egg-info/entry_points.txt
genesisclient.egg-info/requires.txt
genesisclient.egg-info/top_level.txt