Metadata-Version: 1.0
Name: genesisclient
Version: 0.0.7
Summary: Genesis (DeStatis et. al.) client for Python
Home-page: https://github.com/marians/genesisclient
Author: Marian Steinbach
Author-email: marian@sendung.de
License: MIT
Platform: UNKNOWN
